fuzzpyxl/__init__.py
fuzzpyxl/cell_compare/__init__.py
fuzzpyxl/cell_compare/alignment.py
fuzzpyxl/cell_compare/base.py
fuzzpyxl/cell_compare/border.py
fuzzpyxl/cell_compare/cell_type.py
fuzzpyxl/cell_compare/color.py
fuzzpyxl/cell_compare/data_type.py
fuzzpyxl/cell_compare/font.py
fuzzpyxl/cell_compare/ignore.py
fuzzpyxl/cell_compare/regex.py
fuzzpyxl/cell_compare/value.py
fuzzpyxl/finder.py
fuzzpyxl/utils/__init__.py
fuzzpyxl/utils/color_utils.py
fuzzpyxl-0.0.4.dist-info/entry_points.txt
fuzzpyxl-0.0.4.dist-info/LICENSE.md
fuzzpyxl-0.0.4.dist-info/WHEEL
fuzzpyxl-0.0.4.dist-info/METADATA
fuzzpyxl-0.0.4.dist-info/RECORD
